nevolution_risk/__init__.py
nevolution_risk/constants/__init__.py
nevolution_risk/constants/colors.py
nevolution_risk/constants/constants.py
nevolution_risk/constants/view_settings.py
nevolution_risk/res/continents.txt
nevolution_risk/res/debug_graph
nevolution_risk/res/pixel_matrix.pickle
nevolution_risk/res/relative_position_x.txt
nevolution_risk/res/relative_position_y.txt
nevolution_risk/res/small.txt
nevolution_risk/res/sword.png
nevolution_risk/res/test.jpg
nevolution_risk/res/test.png
nevolution_risk/res/void-mask.xbm
nevolution_risk/res/void.xbm
nevolution_risk/res/output/0.png
nevolution_risk/res/output/1.png
nevolution_risk/res/output/10.png
nevolution_risk/res/output/11.png
nevolution_risk/res/output/12.png
nevolution_risk/res/output/13.png
nevolution_risk/res/output/14.png
nevolution_risk/res/output/15.png
nevolution_risk/res/output/16.png
nevolution_risk/res/output/17.png
nevolution_risk/res/output/18.png
nevolution_risk/res/output/19.png
nevolution_risk/res/output/2.png
nevolution_risk/res/output/20.png
nevolution_risk/res/output/21.png
nevolution_risk/res/output/22.png
nevolution_risk/res/output/23.png
nevolution_risk/res/output/24.png
nevolution_risk/res/output/25.png
nevolution_risk/res/output/26.png
nevolution_risk/res/output/27.png
nevolution_risk/res/output/28.png
nevolution_risk/res/output/29.png
nevolution_risk/res/output/3.png
nevolution_risk/res/output/30.png
nevolution_risk/res/output/31.png
nevolution_risk/res/output/32.png
nevolution_risk/res/output/33.png
nevolution_risk/res/output/34.png
nevolution_risk/res/output/35.png
nevolution_risk/res/output/36.png
nevolution_risk/res/output/37.png
nevolution_risk/res/output/38.png
nevolution_risk/res/output/39.png
nevolution_risk/res/output/4.png
nevolution_risk/res/output/40.png
nevolution_risk/res/output/41.png
nevolution_risk/res/output/5.png
nevolution_risk/res/output/6.png
nevolution_risk/res/output/7.png
nevolution_risk/res/output/8.png
nevolution_risk/res/output/9.png
nevolution_risk-202.dist-info/METADATA
nevolution_risk-202.dist-info/WHEEL
nevolution_risk-202.dist-info/top_level.txt
nevolution_risk-202.dist-info/RECORD
