Metadata-Version: 2.1
Name: nevolution-risk
Version: 202
Summary: Python Gym Environment for the popular Risk game
Home-page: https://gitlab.com/nevolution.developers/slave/games/risk
Author: nevolution.developers
Author-email: basti.neubert@gmail.com
License: UNKNOWN
Platform: UNKNOWN
Classifier: Programming Language :: Python :: 3.6
Classifier: License :: OSI Approved :: MIT License
Classifier: Operating System :: OS Independent
Requires-Dist: networkx
Requires-Dist: pygame
Requires-Dist: numpy
Requires-Dist: gym
Requires-Dist: pytest
